odoo/addons/base_user_empty_password/README.rst
odoo/addons/base_user_empty_password/__init__.py
odoo/addons/base_user_empty_password/__manifest__.py
odoo/addons/base_user_empty_password/i18n/base_user_empty_password.pot
odoo/addons/base_user_empty_password/i18n/it.po
odoo/addons/base_user_empty_password/models/__init__.py
odoo/addons/base_user_empty_password/models/res_users.py
odoo/addons/base_user_empty_password/readme/CONTRIBUTORS.md
odoo/addons/base_user_empty_password/readme/CREDITS.md
odoo/addons/base_user_empty_password/readme/DESCRIPTION.md
odoo/addons/base_user_empty_password/security/ir.model.access.csv
odoo/addons/base_user_empty_password/static/description/icon.png
odoo/addons/base_user_empty_password/static/description/index.html
odoo/addons/base_user_empty_password/tests/__init__.py
odoo/addons/base_user_empty_password/tests/test_user_empty_password.py
odoo/addons/base_user_empty_password/views/res_users.xml
odoo/addons/base_user_empty_password/wizard/__init__.py
odoo/addons/base_user_empty_password/wizard/empty_password.py
odoo/addons/base_user_empty_password/wizard/empty_password.xml
odoo_addon_base_user_empty_password-18.0.1.0.0.5.dist-info/METADATA
odoo_addon_base_user_empty_password-18.0.1.0.0.5.dist-info/WHEEL
odoo_addon_base_user_empty_password-18.0.1.0.0.5.dist-info/top_level.txt
odoo_addon_base_user_empty_password-18.0.1.0.0.5.dist-info/RECORD
